CHANGES.txt
CONTRIBUTORS.md
DESC.txt
LICENSE.txt
MANIFEST.in
README.md
README.txt
requirements.txt
setup.py
EasySettings.egg-info/PKG-INFO
EasySettings.egg-info/SOURCES.txt
EasySettings.egg-info/dependency_links.txt
EasySettings.egg-info/requires.txt
EasySettings.egg-info/top_level.txt
docs/gpl.txt
easysettings/__init__.py
easysettings/__main__.py
easysettings/common_base.py
easysettings/easy_settings.py
easysettings/json_settings.py
easysettings/test_easysettings.py
easysettings/test_settingsbase.py
easysettings/toml_settings.py
easysettings/yaml_settings.py