Metadata-Version: 2.1
Name: EasySettings
Version: 4.0.0
Summary: Easily set and retrieve application settings.
